setup.py
ljz_distributions/Binomialdistribution.py
ljz_distributions/Gaussiandistribution.py
ljz_distributions/Generaldistribution.py
ljz_distributions/__init__.py
ljz_distributions/love.py
ljz_distributions.egg-info/PKG-INFO
ljz_distributions.egg-info/SOURCES.txt
ljz_distributions.egg-info/dependency_links.txt
ljz_distributions.egg-info/not-zip-safe
ljz_distributions.egg-info/top_level.txt