Metadata-Version: 1.0
Name: ljz-distributions
Version: 0.21
Summary: Gaussian and Binomial distributions
Home-page: UNKNOWN
Author: Jinze Li
Author-email: lijinze0704@gmail.com
License: UNKNOWN
Platform: UNKNOWN
